entityspine/__init__.py
entityspine/adapters/__init__.py
entityspine/adapters/json_store.py
entityspine/adapters/protocol.py
entityspine/adapters/orm/__init__.py
entityspine/adapters/orm/engine.py
entityspine/adapters/orm/sqlmodel_store.py
entityspine/adapters/orm/tables.py
entityspine/adapters/orm/repositories/__init__.py
entityspine/adapters/orm/repositories/base.py
entityspine/adapters/orm/repositories/claim_repo.py
entityspine/adapters/orm/repositories/entity_repo.py
entityspine/adapters/orm/repositories/listing_repo.py
entityspine/adapters/orm/repositories/security_repo.py
entityspine/adapters/pydantic/__init__.py
entityspine/adapters/pydantic/base.py
entityspine/adapters/pydantic/candidate.py
entityspine/adapters/pydantic/claim.py
entityspine/adapters/pydantic/entity.py
entityspine/adapters/pydantic/listing.py
entityspine/adapters/pydantic/resolution.py
entityspine/adapters/pydantic/security.py
entityspine/adapters/pydantic/validators.py
entityspine/core/__init__.py
entityspine/core/config.py
entityspine/core/exceptions.py
entityspine/core/identifier.py
entityspine/core/normalize.py
entityspine/core/timestamps.py
entityspine/core/ulid.py
entityspine/domain/__init__.py
entityspine/domain/candidate.py
entityspine/domain/claim.py
entityspine/domain/entity.py
entityspine/domain/enums.py
entityspine/domain/factories.py
entityspine/domain/graph.py
entityspine/domain/listing.py
entityspine/domain/protocols.py
entityspine/domain/resolution.py
entityspine/domain/security.py
entityspine/domain/timestamps.py
entityspine/domain/validators.py
entityspine/integration/__init__.py
entityspine/integration/contracts.py
entityspine/integration/ingest.py
entityspine/integration/normalize.py
entityspine/stores/__init__.py
entityspine/stores/json_store.py
entityspine/stores/mappers.py
entityspine/stores/sqlite_store.py
entityspine-0.3.3.dist-info/METADATA
entityspine-0.3.3.dist-info/WHEEL
entityspine-0.3.3.dist-info/entry_points.txt
entityspine-0.3.3.dist-info/RECORD
