Metadata-Version: 2.4
Name: entityspine
Version: 0.3.3
Summary: Lightweight entity resolution - from company_tickers.json to enterprise
Project-URL: Homepage, https://github.com/ryansmccoy/entity-spine
Project-URL: Documentation, https://github.com/ryansmccoy/entity-spine/tree/main/docs
Project-URL: Repository, https://github.com/ryansmccoy/entity-spine
Project-URL: Issues, https://github.com/ryansmccoy/entity-spine/issues
Author-email: Ryan McCoy <ryansmccoy@gmail.com>
License: MIT
Keywords: cik,edgar,entity,resolution,sec,ticker
Classifier: Development Status :: 3 - Alpha
Classifier: Intended Audience :: Developers
Classifier: License :: OSI Approved :: MIT License
Classifier: Programming Language :: Python :: 3
Classifier: Programming Language :: Python :: 3.11
Classifier: Programming Language :: Python :: 3.12
Classifier: Programming Language :: Python :: 3.13
Classifier: Topic :: Database
Classifier: Topic :: Office/Business :: Financial
Classifier: Typing :: Typed
Requires-Python: >=3.11
Provides-Extra: api
Requires-Dist: fastapi>=0.115.0; extra == 'api'
Requires-Dist: pydantic-settings>=2.1.0; extra == 'api'
Requires-Dist: pydantic>=2.5.0; extra == 'api'
Requires-Dist: uvicorn[standard]>=0.32.0; extra == 'api'
Provides-Extra: dev
Requires-Dist: httpx>=0.26.0; extra == 'dev'
Requires-Dist: mypy>=1.8.0; extra == 'dev'
Requires-Dist: pre-commit>=3.6.0; extra == 'dev'
Requires-Dist: pydantic>=2.5.0; extra == 'dev'
Requires-Dist: pytest-asyncio>=0.23.0; extra == 'dev'
Requires-Dist: pytest-cov>=4.1.0; extra == 'dev'
Requires-Dist: pytest-mock>=3.12.0; extra == 'dev'
Requires-Dist: pytest>=8.0.0; extra == 'dev'
Requires-Dist: ruff>=0.8.0; extra == 'dev'
Requires-Dist: sqlmodel>=0.0.22; extra == 'dev'
Requires-Dist: types-python-dateutil>=2.8.0; extra == 'dev'
Provides-Extra: docs
Requires-Dist: mkdocs-material>=9.5.0; extra == 'docs'
Requires-Dist: mkdocs>=1.5.0; extra == 'docs'
Requires-Dist: mkdocstrings[python]>=0.24.0; extra == 'docs'
Provides-Extra: duckdb
Requires-Dist: duckdb>=1.0.0; extra == 'duckdb'
Provides-Extra: full
Requires-Dist: asyncpg>=0.29.0; extra == 'full'
Requires-Dist: duckdb>=1.0.0; extra == 'full'
Requires-Dist: elasticsearch>=8.12.0; extra == 'full'
Requires-Dist: fastapi>=0.115.0; extra == 'full'
Requires-Dist: psycopg[binary]>=3.1.0; extra == 'full'
Requires-Dist: pydantic-settings>=2.1.0; extra == 'full'
Requires-Dist: pydantic>=2.5.0; extra == 'full'
Requires-Dist: sqlmodel>=0.0.22; extra == 'full'
Requires-Dist: uvicorn[standard]>=0.32.0; extra == 'full'
Provides-Extra: orm
Requires-Dist: pydantic>=2.5.0; extra == 'orm'
Requires-Dist: sqlmodel>=0.0.22; extra == 'orm'
Provides-Extra: postgres
Requires-Dist: asyncpg>=0.29.0; extra == 'postgres'
Requires-Dist: psycopg[binary]>=3.1.0; extra == 'postgres'
Requires-Dist: sqlmodel>=0.0.22; extra == 'postgres'
Provides-Extra: pydantic
Requires-Dist: pydantic>=2.5.0; extra == 'pydantic'
Provides-Extra: search
Requires-Dist: elasticsearch>=8.12.0; extra == 'search'
